clingraph/__init__.py
clingraph/clingo_utils.py
clingraph/exceptions.py
clingraph/gif.py
clingraph/graphviz.py
clingraph/logger.py
clingraph/orm.py
clingraph/tex.py
clingraph/utils.py
clingraph-1.1.2.dist-info/LICENSE
clingraph-1.1.2.dist-info/METADATA
clingraph-1.1.2.dist-info/WHEEL
clingraph-1.1.2.dist-info/entry_points.txt
clingraph-1.1.2.dist-info/top_level.txt
clingraph-1.1.2.dist-info/RECORD
