Metadata-Version: 2.1
Name: clingraph
Version: 1.1.2
Summary: A visualizer for graphs defined as facts with special integration for clingo
Home-page: https://github.com/potassco/clingraph
Author: Susana Hahn
Author-email: hahnmartinlu@uni-potsdam.de
License: MIT
License-File: LICENSE
Requires-Dist: clingo>=5.5.0
Requires-Dist: clorm>=1.3.6
Requires-Dist: graphviz
Requires-Dist: networkx>=2.6
Requires-Dist: jsonschema
Requires-Dist: jinja2
Provides-Extra: dev
Requires-Dist: pylint==2.12; extra == "dev"
Requires-Dist: pytest>=6.2; extra == "dev"
Provides-Extra: test
Requires-Dist: pytest>=6.2; extra == "test"
Provides-Extra: doc
Requires-Dist: nbsphinx; extra == "doc"
Requires-Dist: sphinx; extra == "doc"
Requires-Dist: sphinx_rtd_theme; extra == "doc"
Provides-Extra: tex
Requires-Dist: dot2tex; extra == "tex"
Provides-Extra: gif
Requires-Dist: imageio==2.28; extra == "gif"
Requires-Dist: pillow; extra == "gif"
